MANIFEST.in
NEWS.txt
README.rst
setup.py
src/etcd/__init__.py
src/etcd/client.py
src/etcd/lock.py
src/etcd/tests/__init__.py
src/etcd/tests/integration/__init__.py
src/etcd/tests/integration/helpers.py
src/etcd/tests/integration/test_simple.py
src/etcd/tests/integration/test_ssl.py
src/etcd/tests/unit/__init__.py
src/etcd/tests/unit/test_client.py
src/etcd/tests/unit/test_lock.py
src/etcd/tests/unit/test_old_request.py
src/etcd/tests/unit/test_request.py
src/etcd/tests/unit/test_result.py
src/python_etcd.egg-info/PKG-INFO
src/python_etcd.egg-info/SOURCES.txt
src/python_etcd.egg-info/dependency_links.txt
src/python_etcd.egg-info/not-zip-safe
src/python_etcd.egg-info/requires.txt
src/python_etcd.egg-info/top_level.txt