Metadata-Version: 1.1
Name: python-etcd
Version: 0.4.2
Summary: A python client for etcd
Home-page: http://github.com/jplana/python-etcd
Author: Jose Plana
Author-email: jplana@gmail.com
License: MIT
Keywords: etcd raft distributed log api client
Platform: UNKNOWN
Classifier: Topic :: System :: Distributed Computing
Classifier: Topic :: Software Development :: Libraries
Classifier: License :: OSI Approved :: MIT License
Classifier: Programming Language :: Python :: 2
Classifier: Programming Language :: Python :: 3
Classifier: Topic :: Database :: Front-Ends
